AUTHORS.rst
CONTRIBUTING.rst
HISTORY.rst
LICENSE
MANIFEST.in
README.rst
setup.cfg
setup.py
docs/Makefile
docs/authors.rst
docs/conf.py
docs/contributing.rst
docs/history.rst
docs/index.rst
docs/installation.rst
docs/make.bat
docs/readme.rst
docs/usage.rst
refchooser/__init__.py
refchooser/cli.py
refchooser/command.py
refchooser/refchooser.py
refchooser/utils.py
refchooser.egg-info/PKG-INFO
refchooser.egg-info/SOURCES.txt
refchooser.egg-info/dependency_links.txt
refchooser.egg-info/entry_points.txt
refchooser.egg-info/not-zip-safe
refchooser.egg-info/requires.txt
refchooser.egg-info/top_level.txt
tests/__init__.py
tests/test_cli.py
tests/test_refchooser.py
tests/test_utils.py