Metadata-Version: 1.1
Name: refchooser
Version: 0.2.1
Summary: Tools to help choosing a reference assembly.
Home-page: https://github.com/CFSAN-Biostatistics/refchooser
Author: Steve Davis
Author-email: steven.davis@fda.hhs.gov
License: BSD
Keywords: bioinformatics,NGS,refchooser
Platform: UNKNOWN
Classifier: Development Status :: 4 - Beta
Classifier: Intended Audience :: Developers
Classifier: Intended Audience :: Science/Research
Classifier: License :: OSI Approved :: BSD License
Classifier: Natural Language :: English
Classifier: Programming Language :: Python :: 2
Classifier: Programming Language :: Python :: 2.7
Classifier: Programming Language :: Python :: 3
Classifier: Programming Language :: Python :: 3.4
Classifier: Programming Language :: Python :: 3.5
Classifier: Programming Language :: Python :: 3.6
Classifier: Programming Language :: Python :: 3.7
